{
  "manifest": {
    "apis": {
      "custom": {
        "endpoint": {
          "sourceDir": "lambda/custom"
        },
        "interfaces": []
      }
    },
    "manifestVersion": "1.0",
    "privacyAndCompliance": {
      "locales": {
        "ja-JP": {}
      }
    },
    "publishingInformation": {
      "locales": {
        "ja-JP": {
          "name": "プリンター連携のサンプル",
          "summary": "Sample Short Description",
          "description": "Sample Full Description",
          "examplePhrases": [
            "Alexa open hello world",
            "hello",
            "help"
          ],
          "keywords": []
        }
      },
      "isAvailableWorldwide": true,
      "testingInstructions": "Sample Testing Instructions.",
      "category": "KNOWLEDGE_AND_TRIVIA",
      "distributionCountries": []
    }
  }
}
